pyxplor/__init__.py
pyxplor/plot_binary.py
pyxplor/plot_categorical.py
pyxplor/plot_numeric.py
pyxplor/plot_time_series.py
pyxplor-2.0.11.dist-info/LICENSE
pyxplor-2.0.11.dist-info/METADATA
pyxplor-2.0.11.dist-info/WHEEL
pyxplor-2.0.11.dist-info/RECORD
