Metadata-Version: 2.1
Name: pyxplor
Version: 2.0.11
Summary: A package for simplifying the EDA of different data types!
License: MIT
Author: Ben Chen Rachel Bouwer Arturo Boquin Iris Luo
Requires-Python: >=3.9
Classifier: License :: OSI Approved :: MIT License
Classifier: Programming Language :: Python :: 3
Classifier: Programming Language :: Python :: 3.9
Classifier: Programming Language :: Python :: 3.10
Classifier: Programming Language :: Python :: 3.11
Classifier: Programming Language :: Python :: 3.12
Requires-Dist: matplotlib (>=3.8.2)
Requires-Dist: numpy (>=1.26.3)
Requires-Dist: pandas (>=2.1.4)
Requires-Dist: seaborn (>=0.13.1)
